equinox/__init__.py
equinox/asgi.py
equinox/serializers.py
equinox/settings.py
equinox/urls.py
equinox/views.py
equinox/wsgi.py
equinox_server-0.3.dist-info/LICENSE.txt
equinox_server-0.3.dist-info/METADATA
equinox_server-0.3.dist-info/WHEEL
equinox_server-0.3.dist-info/top_level.txt
equinox_server-0.3.dist-info/RECORD
