Metadata-Version: 2.1
Name: equinox-server
Version: 0.3
Summary: An open source platform for sustainable finance
Home-page: https://github.com/open-risk/equinox
Author: Open Risk
Author-email: info@openrisk.eu
License: Apache
Keywords: sustainable finance,ghg emissions,pcaf,eeio,portfolio,loan,database
Platform: UNKNOWN
Classifier: Environment :: Web Environment
Classifier: Intended Audience :: Developers
Classifier: Intended Audience :: Science/Research
Classifier: Intended Audience :: Financial and Insurance Industry
Classifier: Development Status :: 3 - Alpha
Classifier: License :: OSI Approved :: Apache Software License
Classifier: Operating System :: OS Independent
Classifier: Programming Language :: Python :: 3 :: Only
Classifier: Programming Language :: Python :: 3.9
Classifier: Topic :: Scientific/Engineering
Classifier: Topic :: Scientific/Engineering :: Information Analysis
Provides: equinox
Requires-Python: >=3.9
License-File: LICENSE.txt
Requires-Dist: Django
